setup.py
gtwittools/__init__.py
gtwittools/gutils.py
gtwittools/tumblin.py
gtwittools/tweetin.py
gtwittools.egg-info/PKG-INFO
gtwittools.egg-info/SOURCES.txt
gtwittools.egg-info/dependency_links.txt
gtwittools.egg-info/requires.txt
gtwittools.egg-info/top_level.txt