Metadata-Version: 1.0
Name: gtwittools
Version: 0.0.1
Summary: Some tools for making twitter-related things with gevent.
Home-page: https://github.com/awentzonline/gtwittools
Author: Adam Wentz
Author-email: awentz@theonion.com
License: MIT
Platform: UNKNOWN
